plz/__init__.py
plz/colorize.py
plz/config.py
plz/glob_tools.py
plz/main.py
plz/runner.py
plz/schema/__init__.py
plz/schema/v1.py
plz/schema/v2.py
plz_cmd-1.2.2.dist-info/entry_points.txt
plz_cmd-1.2.2.dist-info/LICENSE
plz_cmd-1.2.2.dist-info/WHEEL
plz_cmd-1.2.2.dist-info/METADATA
plz_cmd-1.2.2.dist-info/RECORD
