Metadata-Version: 2.1
Name: plz-cmd
Version: 1.2.2
Summary: command line app for running configurable shell commands
Home-page: https://github.com/m3brown/plz
License: MIT
Author: Mike Brown
Author-email: mike.brown@excella.com
Requires-Python: >=3.6,<4.0
Classifier: License :: OSI Approved :: MIT License
Classifier: Programming Language :: Python :: 3
Classifier: Programming Language :: Python :: 3.6
Classifier: Programming Language :: Python :: 3.7
Classifier: Programming Language :: Python :: 3.8
Classifier: Programming Language :: Python :: 3.9
Classifier: Programming Language :: Python :: 3.10
Classifier: Programming Language :: Python :: 3.11
Requires-Dist: PyYAML (>=3.0)
Requires-Dist: colorama (>=0.4.0)
Requires-Dist: jsonschema (>=3.2.0,<4.0.0); python_version < "3.7"
Requires-Dist: jsonschema (>=4.2.0); python_version >= "3.7"
Project-URL: Repository, https://github.com/m3brown/plz
